batgrl/__init__.py
batgrl/_batgrl_markdown.py
batgrl/_rendering.c
batgrl/_rendering.cpython-313-x86_64-linux-gnu.so
batgrl/_rendering.pxd
batgrl/_rendering.pyx
batgrl/_sixel.c
batgrl/_sixel.cpython-313-x86_64-linux-gnu.so
batgrl/_sixel.pxd
batgrl/_sixel.pyx
batgrl/_style.py
batgrl/app.py
batgrl/array_types.py
batgrl/emojis.py
batgrl/figfont.py
batgrl/logging.py
batgrl/py.typed
batgrl/spinners.py
batgrl/text_tools.py
batgrl/texture_tools.py
batgrl/colors/__init__.py
batgrl/colors/color_types.py
batgrl/colors/colors.py
batgrl/colors/gradients.py
batgrl/gadgets/__init__.py
batgrl/gadgets/_raycasting.c
batgrl/gadgets/_raycasting.cpython-313-x86_64-linux-gnu.so
batgrl/gadgets/_raycasting.pyx
batgrl/gadgets/_root.py
batgrl/gadgets/_shadow_casting.c
batgrl/gadgets/_shadow_casting.cpython-313-x86_64-linux-gnu.so
batgrl/gadgets/_shadow_casting.pyx
batgrl/gadgets/animation.py
batgrl/gadgets/ans_viewer.py
batgrl/gadgets/bar_chart.py
batgrl/gadgets/button.py
batgrl/gadgets/color_picker.py
batgrl/gadgets/console.py
batgrl/gadgets/cursor.py
batgrl/gadgets/data_table.py
batgrl/gadgets/digital_display.py
batgrl/gadgets/file_chooser.py
batgrl/gadgets/flat_toggle.py
batgrl/gadgets/gadget.py
batgrl/gadgets/graphic_field.py
batgrl/gadgets/graphics.py
batgrl/gadgets/grid_layout.py
batgrl/gadgets/image.py
batgrl/gadgets/line_plot.py
batgrl/gadgets/markdown.py
batgrl/gadgets/menu.py
batgrl/gadgets/pane.py
batgrl/gadgets/parallax.py
batgrl/gadgets/progress_bar.py
batgrl/gadgets/raycaster.py
batgrl/gadgets/recycle_view.py
batgrl/gadgets/scroll_view.py
batgrl/gadgets/shadow_caster.py
batgrl/gadgets/slider.py
batgrl/gadgets/sparkline.py
batgrl/gadgets/split_layout.py
batgrl/gadgets/stack_layout.py
batgrl/gadgets/tabs.py
batgrl/gadgets/text.py
batgrl/gadgets/text_animation.py
batgrl/gadgets/text_field.py
batgrl/gadgets/text_pad.py
batgrl/gadgets/text_raycaster.py
batgrl/gadgets/textbox.py
batgrl/gadgets/tiled.py
batgrl-0.51.3.dist-info/METADATA
batgrl-0.51.3.dist-info/WHEEL
batgrl-0.51.3.dist-info/top_level.txt
batgrl-0.51.3.dist-info/RECORD
batgrl-0.51.3.dist-info/licenses/LICENSE.Apache-2.0
batgrl-0.51.3.dist-info/licenses/LICENSE.MIT
