Metadata-Version: 2.4
Name: batgrl
Version: 0.51.3
Summary: badass terminal graphics library
Author-email: salt-die <salt-die@protonmail.com>
License-Expression: MIT AND Apache-2.0
Project-URL: repository, https://github.com/salt-die/batgrl
Project-URL: documentation, https://salt-die.github.io/batgrl/index.html
Classifier: Programming Language :: Python :: 3
Classifier: Operating System :: OS Independent
Requires-Python: >=3.12
License-File: LICENSE.Apache-2.0
License-File: LICENSE.MIT
Requires-Dist: mistletoe>=1.3.0
Requires-Dist: numpy>=2.3.4
Requires-Dist: opencv-python>=4.10.0
Requires-Dist: tree_sitter>=0.25.0
Requires-Dist: tree_sitter_python>=0.23.6
Requires-Dist: tree_sitter_regex>=0.24.3
Requires-Dist: tree_sitter_comment>=0.3.0
Requires-Dist: typing_extensions>=4.14.0
Requires-Dist: ugrapheme>=0.8
Requires-Dist: uwcwidth>=1.0.0
Dynamic: license-file
